LICENSE.txt
MANIFEST.in
README
requirements.txt
setup.py
ewsgi/__init__.py
ewsgi/info.py
ewsgi/run.py
ewsgi.egg-info/PKG-INFO
ewsgi.egg-info/SOURCES.txt
ewsgi.egg-info/dependency_links.txt
ewsgi.egg-info/requires.txt
ewsgi.egg-info/top_level.txt
ewsgi/server/__init__.py
ewsgi/server/wsgi.py