Metadata-Version: 1.1
Name: ewsgi
Version: 0.0.3
Summary: Generic Eventlet WSGI server built to serve Python Apps
Home-page: https://github.com/cloudnull/ewsgi
Author: Kevin Carter
Author-email: kevin.carter@RACKSPACE.COM
License: GNU General Public License v3 or later (GPLv3+)
Platform: UNKNOWN
Classifier: Development Status :: 5 - Production/Stable
Classifier: Intended Audience :: Information Technology
Classifier: Intended Audience :: System Administrators
Classifier: Intended Audience :: Developers
Classifier: Operating System :: OS Independent
Classifier: License :: OSI Approved :: GNU General Public License v3 or later (GPLv3+)
Classifier: Programming Language :: Python :: 2.6
Classifier: Programming Language :: Python :: 2.7
Classifier: Topic :: Utilities
Classifier: Topic :: Software Development :: Libraries :: Python Modules
